[
{
	"img":"img/sign1.jpg",
	"title":"熟悉AngularJs",
	"no":"no120",
	"price":10000
},
{
	"img":"img/sign2.png",
	"title":"熟悉AngularJs",
	"no":"no120",
	"price":10000
},
{
	"img":"img/sign4.png",
	"title":"mac 13 computer",
	"no":"no123",
	"price":12000
},
{
	"img":"img/sign5.png",
	"title":"mac 15 computer",
	"no":"no125",
	"price":14000
},
{
	"img":"img/sign6.jpg",
	"title":"熟悉AngularJs",
	"no":"no120",
	"price":10000
},
{
	"img":"img/sign7.png",
	"title":"熟悉AngularJs",
	"no":"no120",
	"price":10000
},
{
	"img":"img/sign98.jpg",
	"title":"熟悉AngularJs",
	"no":"no120",
	"price":10000
},
{
	"img":"img/sign99.jpg",
	"title":"熟悉AngularJs",
	"no":"no120",
	"price":10000
}

]
